edc_listboard/__init__.py
edc_listboard/apps.py
edc_listboard/dashboard_templates.py
edc_listboard/middleware.py
edc_listboard/models.py
edc_listboard/system_checks.py
edc_listboard/urls.py
edc_listboard/filters/__init__.py
edc_listboard/filters/listboard_filter.py
edc_listboard/filters/listboard_view_filters.py
edc_listboard/migrations/0001_initial.py
edc_listboard/migrations/0002_alter_listboard_options.py
edc_listboard/migrations/0003_alter_listboard_device_created_and_more.py
edc_listboard/migrations/0004_alter_listboard_options_listboard_locale_created_and_more.py
edc_listboard/migrations/0005_remove_listboard_edc_listboa_modifie_a5fdf8_idx_and_more.py
edc_listboard/migrations/__init__.py
edc_listboard/templates/edc_listboard/listboard.html
edc_listboard/templates/edc_listboard/search_form.html
edc_listboard/templates/edc_listboard/buttons/dashboard_button.html
edc_listboard/templates/edc_listboard/include/buttons_column.html
edc_listboard/templates/edc_listboard/include/columns.html
edc_listboard/templates/edc_listboard/include/results_body.html
edc_listboard/templates/edc_listboard/include/results_header.html
edc_listboard/tests/__init__.py
edc_listboard/tests/admin.py
edc_listboard/tests/models.py
edc_listboard/tests/test_settings.py
edc_listboard/tests/urls.py
edc_listboard/tests/etc/user-aes-local.key
edc_listboard/tests/etc/user-aes-restricted.key
edc_listboard/tests/etc/user-rsa-local-private.pem
edc_listboard/tests/etc/user-rsa-local-public.pem
edc_listboard/tests/etc/user-rsa-restricted-private.pem
edc_listboard/tests/etc/user-rsa-restricted-public.pem
edc_listboard/tests/etc/user-salt-local.key
edc_listboard/tests/etc/user-salt-restricted.key
edc_listboard/tests/tests/__init__.py
edc_listboard/tests/tests/test_view_mixins.py
edc_listboard/view_mixins/__init__.py
edc_listboard/view_mixins/listboard_filter_view_mixin.py
edc_listboard/view_mixins/querystring_view_mixin.py
edc_listboard/view_mixins/search_form_view_mixin.py
edc_listboard-1.0.0.dist-info/AUTHORS
edc_listboard-1.0.0.dist-info/LICENSE
edc_listboard-1.0.0.dist-info/METADATA
edc_listboard-1.0.0.dist-info/WHEEL
edc_listboard-1.0.0.dist-info/top_level.txt
edc_listboard-1.0.0.dist-info/RECORD
